drf_turbo/__init__.py
drf_turbo/cython_metaclass.c
drf_turbo/cython_metaclass.cpython-38-darwin.so
drf_turbo/exceptions.c
drf_turbo/exceptions.cpython-38-darwin.so
drf_turbo/fields.c
drf_turbo/fields.cpython-38-darwin.so
drf_turbo/meta.py
drf_turbo/openapi.py
drf_turbo/serializer.c
drf_turbo/serializer.cpython-38-darwin.so
drf_turbo/utils.c
drf_turbo/utils.cpython-38-darwin.so
drf_turbo-0.1.7.dist-info/AUTHORS.rst
drf_turbo-0.1.7.dist-info/LICENSE
drf_turbo-0.1.7.dist-info/METADATA
drf_turbo-0.1.7.dist-info/WHEEL
drf_turbo-0.1.7.dist-info/top_level.txt
drf_turbo-0.1.7.dist-info/RECORD
