Metadata-Version: 2.1
Name: drf-turbo
Version: 0.1.7
Summary: An alternative serializer implementation for REST framework written in cython built for speed.
Home-page: https://github.com/Mng-dev-ai/drf-turbo
Author: Michael Gendy
Author-email: nagymichel13@gmail.com
License: MIT license
Keywords: drf_turbo
Classifier: Development Status :: 4 - Beta
Classifier: Intended Audience :: Developers
Classifier: License :: OSI Approved :: MIT License
Classifier: Natural Language :: English
Classifier: Programming Language :: Python :: 3.8
Classifier: Programming Language :: Python :: 3.9
Requires-Python: >=3.8, <3.10
License-File: LICENSE
License-File: AUTHORS.rst
Requires-Dist: forbiddenfruit (==0.1.4)
Requires-Dist: djangorestframework (==3.12.4)
Requires-Dist: pyyaml (<5.4,>=5.3.1)
Requires-Dist: uritemplate (==4.1.1)
Requires-Dist: djangorestframework-simplejwt (==5.2.0)
Requires-Dist: pytz (==2022.1)
Requires-Dist: django (<4.0,>=3.2.5)
